{
    "timestamp": "07/04/2026 17:19:52",
    "colaborador": "Usuario_Desconhecido",
    "campos": {
        "cargo": "",
        "departamento": "",
        "setor": "",
        "chefe": "",
        "unidade": "",
        "escolaridade": "",
        "cursos": "",
        "objetivo": ""
    },
    "tabelas": {
        "alta": [
            {
                "Atividade": "CCC",
                "Horas": "1 h",
                "Minutos": "20 min",
                "Frequência": "D"
            }
        ],
        "normal": [
            {
                "Atividade": "C",
                "Horas": "2 h",
                "Minutos": "0 min",
                "Frequência": "S"
            }
        ],
        "baixa": [
            {
                "Atividade": "C",
                "Horas": "4 h",
                "Minutos": "30 min",
                "Frequência": "A"
            }
        ],
        "dificuldades": [
            {
                "Dificuldade": "C",
                "Setor Envolvido": "C",
                "Horas": "1 h",
                "Minutos": "5 min",
                "Frequência": "D"
            }
        ],
        "sugestoes": [
            {
                "Sugestão": "C",
                "Impacto Esperado": "C",
                "Horas": "1 h",
                "Minutos": "20 min",
                "Frequência": "D"
            }
        ]
    },
    "disc": {
        "0": "A",
        "1": "A",
        "2": "B",
        "3": "B",
        "4": "B",
        "5": "C",
        "6": "B",
        "7": "A",
        "8": "A",
        "9": "D",
        "10": "D",
        "11": "C",
        "12": "C",
        "13": "B",
        "14": "A",
        "15": "A",
        "16": "A",
        "17": "D",
        "18": "C",
        "19": "B",
        "20": "B",
        "21": "B",
        "22": "A",
        "23": "A"
    }
}