{
    "colaborador": "JUAREZ QUEIROZ PEREIRA",
    "criado_em": "19/04/2026 03:28:55",
    "campos": {
        "cargo": "ANALISTA DEPARTAMENTO PESSOAL",
        "dep": "DP",
        "setor": "DP",
        "chefe": "ADSON",
        "unidade": "JV CONTABILIDADE",
        "escolaridade": "NÍVEL SUPERIOR COMPLETO",
        "cursos": "Ciências Contábeis, Pacote Office Avançado, Sistemas Folhas Pagamento: RM Sistema Totvs, ERP/RM,\\n Questor, Alterdata, Domínios, GCI, RH3, RH3 Ponto, Ferramenta Pontomais, RH3 Benefícios, RH3 Gerador de\\nRelatórios, EBS Cordilheira, Microsiga, Rubi, Ponto Eletrônico Radar, Chronos Labore e Honda Portaria 1510,\\nAtualizado com o E-SOCIAL, FGTS Digital, Power BI, Curso SENAI Competências Transversais em Legislação\\nTrabalhista, Financeiro SAP, Windows, Word, Excel Avançado.",
        "objetivo": "Meu trabalho no Departamento Pessoal (DP) consiste em cuidar de toda a parte administrativa e legal relacionada aos colaboradores de uma empresa e clientes. Isso envolve garantir que a relação entre empresa e funcionário esteja sempre de acordo com a legislação trabalhista.\\nAdmissão e demissão de funcionários, Controle de ponto (horas trabalhadas, atrasos, faltas, Processamento da folha de pagamento, Cálculo de férias, 13º salário e rescisões\\nGestão de benefícios (vale-transporte, vale alimentação, Envio de obrigações legais ao governo como e Social.\\nAssegurar que todos os direitos e deveres trabalhistas sejam cumpridos corretamente, tanto para a empresa quanto para os colaboradores.\\nAlém disso, o DP busca:\\nEvitar problemas legais e trabalhistas , manter a organização e transparência nos processos internos, garantir que os funcionários recebam corretamente seus pagamentos e benefícios.\\nResumindo: o Departamento Pessoal é essencial para manter a empresa regularizada, organizada e justa nas relações de trabalho."
    },
    "roi": {
        "auditado": 6224.17,
        "bruto": 12833.33,
        "horas_recuperaveis": 177.83,
        "ganho_dias": 22.2,
        "custo_hora": 35.0
    },
    "nexo_causal": {
        "score": 61.0,
        "horas_dia": 14.5,
        "status": "sobrecarga"
    },
    "disc": {
        "percentuais": {
            "D": 42,
            "I": 8,
            "S": 21,
            "C": 29
        },
        "perfil_dominante": "D",
        "score_intensidade": 0,
        "amplitude": 34,
        "is_equilibrado": false,
        "perfil_exigido_tarefas": "C-S",
        "compatibilidade_pct": "N/A",
        "score_alinhamento_cargo": 30,
        "benchmark_cargo": "C-S",
        "veredito_aderencia": "Baixa Aderencia"
    },
    "sugestoes_auditadas": [
        {
            "ESTRATEGIA": "MELHORIA INCREMENTAL",
            "SUGESTAO ANALISADA": "IMPLANTAÇÃO DE PROCESSOS PADRONIZADOS PARA ROTINAS DE ADMISSÃO, DEMISSÃO E FECHAMENTO DE FOLHA, REDUZINDO ERROS E RETRAB",
            "ECONOMIA PROJETADA": "- 7.3 h/ano",
            "VALOR RECUPERAVEL": "R$ 256.67"
        },
        {
            "ESTRATEGIA": "TRANSFORMACAO DIGITAL",
            "SUGESTAO ANALISADA": "CRIAÇÃO DE UM CRONOGRAMA MENSAL INTEGRADO COM TODOS OS SETORES, GARANTINDO O ENVIO DE INFORMAÇÕES DENTRO DOS PRAZOS",
            "ECONOMIA PROJETADA": "- 31.2 h/ano",
            "VALOR RECUPERAVEL": "R$ 1,090.83"
        },
        {
            "ESTRATEGIA": "TRANSFORMACAO DIGITAL",
            "SUGESTAO ANALISADA": "INVESTIMENTO EM AUTOMAÇÃO DE PROCESSOS (SISTEMAS DE FOLHA E PONTO), VISANDO MAIOR AGILIDADE E CONFIABILIDADE NOS DADOS",
            "ECONOMIA PROJETADA": "- 31.2 h/ano",
            "VALOR RECUPERAVEL": "R$ 1,090.83"
        },
        {
            "ESTRATEGIA": "OTIMIZACAO DE PROCESSO",
            "SUGESTAO ANALISADA": "REALIZAÇÃO DE TREINAMENTOS PERIÓDICOS PARA GESTORES E COLABORADORES SOBRE ROTINAS TRABALHISTAS E USO CORRETO DO PONTO EL",
            "ECONOMIA PROJETADA": "- 16.5 h/ano",
            "VALOR RECUPERAVEL": "R$ 577.50"
        },
        {
            "ESTRATEGIA": "TRANSFORMACAO DIGITAL",
            "SUGESTAO ANALISADA": "MELHORIA NA INTEGRAÇÃO ENTRE OS SISTEMAS (FOLHA, PONTO E BENEFÍCIOS), EVITANDO DIVERGÊNCIAS DE INFORMAÇÕES",
            "ECONOMIA PROJETADA": "- 31.2 h/ano",
            "VALOR RECUPERAVEL": "R$ 1,090.83"
        },
        {
            "ESTRATEGIA": "MELHORIA INCREMENTAL",
            "SUGESTAO ANALISADA": "DESENVOLVIMENTO DE INDICADORES (KPIS) PARA ACOMPANHAMENTO DE ERROS, RETRABALHO E CUMPRIMENTO DE PRAZOS",
            "ECONOMIA PROJETADA": "- 7.3 h/ano",
            "VALOR RECUPERAVEL": "R$ 256.67"
        },
        {
            "ESTRATEGIA": "MELHORIA INCREMENTAL",
            "SUGESTAO ANALISADA": "CENTRALIZAÇÃO E DIGITALIZAÇÃO DE DOCUMENTOS, FACILITANDO O ACESSO E REDUZINDO PERDAS DE INFORMAÇÃO",
            "ECONOMIA PROJETADA": "- 7.3 h/ano",
            "VALOR RECUPERAVEL": "R$ 256.67"
        },
        {
            "ESTRATEGIA": "TRANSFORMACAO DIGITAL",
            "SUGESTAO ANALISADA": "CRIAÇÃO DE CANAIS DE COMUNICAÇÃO MAIS CLAROS COM COLABORADORES PARA ESCLARECIMENTO DE DÚVIDAS SOBRE FOLHA, BENEFÍCIOS E ",
            "ECONOMIA PROJETADA": "- 31.2 h/ano",
            "VALOR RECUPERAVEL": "R$ 1,090.83"
        },
        {
            "ESTRATEGIA": "MELHORIA INCREMENTAL",
            "SUGESTAO ANALISADA": "REVISÃO CONTÍNUA DOS PROCESSOS INTERNOS PARA ADEQUAÇÃO ÀS MUDANÇAS NA LEGISLAÇÃO TRABALHISTA",
            "ECONOMIA PROJETADA": "- 7.3 h/ano",
            "VALOR RECUPERAVEL": "R$ 256.67"
        },
        {
            "ESTRATEGIA": "MELHORIA INCREMENTAL",
            "SUGESTAO ANALISADA": "REDUÇÃO DE ATIVIDADES OPERACIONAIS POR MEIO DE DELEGAÇÃO OU AUTOMAÇÃO, PERMITINDO MAIOR FOCO EM ANÁLISES ESTRATÉGICAS",
            "ECONOMIA PROJETADA": "- 7.3 h/ano",
            "VALOR RECUPERAVEL": "R$ 256.67"
        }
    ],
    "gargalos": [
        {
            "Status": "✅",
            "Setor": "DP",
            "Dificuldade": "Dependência de informações de outros setores (gestores, ponto, RH) para execução correta das rotinas",
            "Impacto Diario": "0.583 h/dia",
            "Analise do Perito": "Aguardando auditoria de nexo causal"
        },
        {
            "Status": "✅",
            "Setor": "DP",
            "Dificuldade": "Frequentes alterações na legislação trabalhista e fiscal, exigindo atualização constante",
            "Impacto Diario": "0.583 h/dia",
            "Analise do Perito": "Aguardando auditoria de nexo causal"
        },
        {
            "Status": "✅",
            "Setor": "DP",
            "Dificuldade": "Inconsistências em registros de ponto e dados cadastrais dos colaboradores",
            "Impacto Diario": "0.583 h/dia",
            "Analise do Perito": "Aguardando auditoria de nexo causal"
        },
        {
            "Status": "✅",
            "Setor": "DP",
            "Dificuldade": "Ocorrência de retrabalho devido a informações incompletas ou enviadas fora do prazo",
            "Impacto Diario": "0.583 h/dia",
            "Analise do Perito": "Aguardando auditoria de nexo causal"
        },
        {
            "Status": "✅",
            "Setor": "DP",
            "Dificuldade": "Limitações e instabilidades nos sistemas (folha, ponto, eSocial), principalmente em períodos críticos",
            "Impacto Diario": "0.583 h/dia",
            "Analise do Perito": "Aguardando auditoria de nexo causal"
        },
        {
            "Status": "✅",
            "Setor": "DP",
            "Dificuldade": "Dificuldade na padronização de processos e fluxos internos",
            "Impacto Diario": "0.583 h/dia",
            "Analise do Perito": "Aguardando auditoria de nexo causal"
        },
        {
            "Status": "✅",
            "Setor": "DP",
            "Dificuldade": "Acúmulo de atividades operacionais que reduz o tempo disponível para análises estratégicas",
            "Impacto Diario": "0.583 h/dia",
            "Analise do Perito": "Aguardando auditoria de nexo causal"
        },
        {
            "Status": "✅",
            "Setor": "DP",
            "Dificuldade": "Necessidade constante de conferência detalhada para evitar erros com impacto legal e financeiro",
            "Impacto Diario": "0.583 h/dia",
            "Analise do Perito": "Aguardando auditoria de nexo causal"
        },
        {
            "Status": "✅",
            "Setor": "DP",
            "Dificuldade": "Comunicação desafiadora em relação a descontos, benefícios e regras trabalhistas",
            "Impacto Diario": "0.583 h/dia",
            "Analise do Perito": "Aguardando auditoria de nexo causal"
        }
    ],
    "auditoria_atividades": [
        {
            "Status": "✅",
            "Atividade": "Fechamento da folha de pagamento (cálculo de salários, encargos, benefícios)",
            "Impacto": "0.583 h/dia",
            "Analise Critica": "Aguardando auditoria — dados do formulário"
        },
        {
            "Status": "✅",
            "Atividade": "Apuração e conferência de encargos trabalhistas (INSS, FGTS, IRRF) ",
            "Impacto": "0.583 h/dia",
            "Analise Critica": "Aguardando auditoria — dados do formulário"
        },
        {
            "Status": "✅",
            "Atividade": "Envio de obrigações acessórias (eSocial, DCTFWeb, SEFIP) ",
            "Impacto": "0.333 h/dia",
            "Analise Critica": "Aguardando auditoria — dados do formulário"
        },
        {
            "Status": "✅",
            "Atividade": "Controle e gestão de admissões e demissões (rescisões, homologações) ",
            "Impacto": "0.333 h/dia",
            "Analise Critica": "Aguardando auditoria — dados do formulário"
        },
        {
            "Status": "✅",
            "Atividade": "Interpretação e aplicação da legislação trabalhista e convenções coletivas ",
            "Impacto": "0.417 h/dia",
            "Analise Critica": "Aguardando auditoria — dados do formulário"
        },
        {
            "Status": "✅",
            "Atividade": "Atendimento internas e externas ",
            "Impacto": "0.500 h/dia",
            "Analise Critica": "Aguardando auditoria — dados do formulário"
        },
        {
            "Status": "✅",
            "Atividade": "Análise de inconsistências na folha e correção de divergências ",
            "Impacto": "0.500 h/dia",
            "Analise Critica": "Aguardando auditoria — dados do formulário"
        },
        {
            "Status": "✅",
            "Atividade": "Gestão de benefícios (vale-transporte, vale-alimentação, plano de saúde) ",
            "Impacto": "0.333 h/dia",
            "Analise Critica": "Aguardando auditoria — dados do formulário"
        },
        {
            "Status": "✅",
            "Atividade": " Lançamento de informações para folha de pagamento (horas extras, faltas, adicionais) ",
            "Impacto": "0.417 h/dia",
            "Analise Critica": "Aguardando auditoria — dados do formulário"
        },
        {
            "Status": "✅",
            "Atividade": "Controle de ponto eletrônico e tratamento de inconsistências",
            "Impacto": "0.250 h/dia",
            "Analise Critica": "Aguardando auditoria — dados do formulário"
        },
        {
            "Status": "✅",
            "Atividade": "Administração de férias (programação, cálculo e controle)",
            "Impacto": "0.333 h/dia",
            "Analise Critica": "Aguardando auditoria — dados do formulário"
        },
        {
            "Status": "✅",
            "Atividade": "Cadastro e atualização de dados de colaboradores no sistema",
            "Impacto": "0.167 h/dia",
            "Analise Critica": "Aguardando auditoria — dados do formulário"
        },
        {
            "Status": "✅",
            "Atividade": "Controle de afastamentos (INSS, atestados médicos, licenças)",
            "Impacto": "0.250 h/dia",
            "Analise Critica": "Aguardando auditoria — dados do formulário"
        },
        {
            "Status": "✅",
            "Atividade": "Atendimento a colaboradores para esclarecimento de dúvidas trabalhistas",
            "Impacto": "0.333 h/dia",
            "Analise Critica": "Aguardando auditoria — dados do formulário"
        },
        {
            "Status": "✅",
            "Atividade": "Organização e conferência de documentação admissional e demissional",
            "Impacto": "0.333 h/dia",
            "Analise Critica": "Aguardando auditoria — dados do formulário"
        },
        {
            "Status": "✅",
            "Atividade": "Apoio no processo de admissão e integração de novos colaboradores ",
            "Impacto": "0.667 h/dia",
            "Analise Critica": "Aguardando auditoria — dados do formulário"
        },
        {
            "Status": "✅",
            "Atividade": "Emissão de relatórios operacionais (folha, ponto, benefícios)",
            "Impacto": "0.167 h/dia",
            "Analise Critica": "Aguardando auditoria — dados do formulário"
        },
        {
            "Status": "✅",
            "Atividade": "Controle de benefícios (inclusão, exclusão e ajustes) ",
            "Impacto": "0.333 h/dia",
            "Analise Critica": "Aguardando auditoria — dados do formulário"
        },
        {
            "Status": "✅",
            "Atividade": "Arquivamento e organização de documentos físicos e digitais ",
            "Impacto": "0.250 h/dia",
            "Analise Critica": "Aguardando auditoria — dados do formulário"
        },
        {
            "Status": "✅",
            "Atividade": "Digitalização de documentos de colaboradores ",
            "Impacto": "0.250 h/dia",
            "Analise Critica": "Aguardando auditoria — dados do formulário"
        },
        {
            "Status": "✅",
            "Atividade": "Atualização simples de planilhas de controle ",
            "Impacto": "0.250 h/dia",
            "Analise Critica": "Aguardando auditoria — dados do formulário"
        },
        {
            "Status": "✅",
            "Atividade": "Conferência básica de documentos (checklist admissional/demissional)",
            "Impacto": "0.333 h/dia",
            "Analise Critica": "Aguardando auditoria — dados do formulário"
        },
        {
            "Status": "✅",
            "Atividade": "Emissão de documentos padronizados (declarações, comprovantes)",
            "Impacto": "0.417 h/dia",
            "Analise Critica": "Aguardando auditoria — dados do formulário"
        },
        {
            "Status": "✅",
            "Atividade": "Apoio no envio de comunicados internos",
            "Impacto": "0.250 h/dia",
            "Analise Critica": "Aguardando auditoria — dados do formulário"
        },
        {
            "Status": "✅",
            "Atividade": "Separação de documentos para processos internos ",
            "Impacto": "0.250 h/dia",
            "Analise Critica": "Aguardando auditoria — dados do formulário"
        },
        {
            "Status": "✅",
            "Atividade": "Atualização de cadastros simples no sistema",
            "Impacto": "0.250 h/dia",
            "Analise Critica": "Aguardando auditoria — dados do formulário"
        },
        {
            "Status": "✅",
            "Atividade": "Controle de recebimento de documentos pendentes",
            "Impacto": "0.167 h/dia",
            "Analise Critica": "Aguardando auditoria — dados do formulário"
        },
        {
            "Status": "✅",
            "Atividade": "Dependência de informações de outros setores (gestores, ponto, RH) para execução correta das rotinas",
            "Impacto": "0.583 h/dia",
            "Analise Critica": "Aguardando auditoria — dados do formulário"
        },
        {
            "Status": "✅",
            "Atividade": "Frequentes alterações na legislação trabalhista e fiscal, exigindo atualização constante",
            "Impacto": "0.583 h/dia",
            "Analise Critica": "Aguardando auditoria — dados do formulário"
        },
        {
            "Status": "✅",
            "Atividade": "Inconsistências em registros de ponto e dados cadastrais dos colaboradores",
            "Impacto": "0.583 h/dia",
            "Analise Critica": "Aguardando auditoria — dados do formulário"
        },
        {
            "Status": "✅",
            "Atividade": "Ocorrência de retrabalho devido a informações incompletas ou enviadas fora do prazo",
            "Impacto": "0.583 h/dia",
            "Analise Critica": "Aguardando auditoria — dados do formulário"
        },
        {
            "Status": "✅",
            "Atividade": "Limitações e instabilidades nos sistemas (folha, ponto, eSocial), principalmente em períodos crítico",
            "Impacto": "0.583 h/dia",
            "Analise Critica": "Aguardando auditoria — dados do formulário"
        },
        {
            "Status": "✅",
            "Atividade": "Dificuldade na padronização de processos e fluxos internos",
            "Impacto": "0.583 h/dia",
            "Analise Critica": "Aguardando auditoria — dados do formulário"
        },
        {
            "Status": "✅",
            "Atividade": "Acúmulo de atividades operacionais que reduz o tempo disponível para análises estratégicas",
            "Impacto": "0.583 h/dia",
            "Analise Critica": "Aguardando auditoria — dados do formulário"
        },
        {
            "Status": "✅",
            "Atividade": "Necessidade constante de conferência detalhada para evitar erros com impacto legal e financeiro",
            "Impacto": "0.583 h/dia",
            "Analise Critica": "Aguardando auditoria — dados do formulário"
        },
        {
            "Status": "✅",
            "Atividade": "Comunicação desafiadora em relação a descontos, benefícios e regras trabalhistas",
            "Impacto": "0.583 h/dia",
            "Analise Critica": "Aguardando auditoria — dados do formulário"
        }
    ],
    "parecer": {
        "pop_padrao_ia": [
            {
                "Atividade": "Gestão_de_Admissões_e_Demissões",
                "Freq": "DIÁRIA",
                "Tempo Base": "60m",
                "Impacto Diário Convertido": "60.0m",
                "Eficiência vs 480m": "12.5%",
                "Meta Auditável": "Completar todos os processos de admissão e demissão em conformidade com as legislações trabalhistas, com um índice de erro máximo de 2% nas auditorias mensais."
            },
            {
                "Atividade": "Controle_de_Ponto",
                "Freq": "DIÁRIA",
                "Tempo Base": "60m",
                "Impacto Diário Convertido": "60.0m",
                "Eficiência vs 480m": "12.5%",
                "Meta Auditável": "Realizar o controle diário de ponto com uma precisão de 98%, garantindo a correta contabilização de horas trabalhadas e ausências."
            },
            {
                "Atividade": "Processamento_da_Folha_de_Pagamento",
                "Freq": "DIÁRIA",
                "Tempo Base": "60m",
                "Impacto Diário Convertido": "60.0m",
                "Eficiência vs 480m": "12.5%",
                "Meta Auditável": "Elaborar, revisar e validar a folha de pagamento mensal com 100% de conformidade legal, observando os prazos estabelecidos."
            },
            {
                "Atividade": "Cálculo_de_Férias_e_13º_Salário",
                "Freq": "DIÁRIA",
                "Tempo Base": "30m",
                "Impacto Diário Convertido": "30.0m",
                "Eficiência vs 480m": "6.2%",
                "Meta Auditável": "Garantir que todos os cálculos de férias e 13º salário sejam realizados com 100% de precisão mensal, evitando quaisquer reincidências de erro."
            },
            {
                "Atividade": "Gestão_de_Benefícios",
                "Freq": "DIÁRIA",
                "Tempo Base": "30m",
                "Impacto Diário Convertido": "30.0m",
                "Eficiência vs 480m": "6.2%",
                "Meta Auditável": "Assegurar a correta gestão dos benefícios fornecidos, com relatórios mensais que apresentem a eficiência na utilização e satisfação dos colaboradores."
            },
            {
                "Atividade": "Envio_de_Obrigações_Legais",
                "Freq": "DIÁRIA",
                "Tempo Base": "30m",
                "Impacto Diário Convertido": "30.0m",
                "Eficiência vs 480m": "6.2%",
                "Meta Auditável": "Realizar o envio de todas as obrigações legais, como eSocial, com 100% de conformidade e dentro dos prazos, validando relatórios trimestrais."
            },
            {
                "Atividade": "Revisão_de_Processos_Legais",
                "Freq": "SEMANAL",
                "Tempo Base": "60m",
                "Impacto Diário Convertido": "12.0m",
                "Eficiência vs 480m": "2.5%",
                "Meta Auditável": "Revisar processos legais e garantir que todas as mudanças na legislação trabalhista sejam implementadas adequadamente, monitorando a conformidade a cada mudança."
            },
            {
                "Atividade": "Auditoria_de_Conformidade",
                "Freq": "SEMANAL",
                "Tempo Base": "60m",
                "Impacto Diário Convertido": "12.0m",
                "Eficiência vs 480m": "2.5%",
                "Meta Auditável": "Realizar auditorias semanais para verificar a conformidade das atividades do departamento pessoal, com um índice de conformidade de 95% ou mais."
            },
            {
                "Atividade": "Relatórios_de_Gestão",
                "Freq": "SEMANAL",
                "Tempo Base": "60m",
                "Impacto Diário Convertido": "12.0m",
                "Eficiência vs 480m": "2.5%",
                "Meta Auditável": "Gerar relatórios gerenciais detalhados sobre a performance do DP e ações corretivas, com reuniões mensais para apresentação dos mesmos."
            },
            {
                "Atividade": "Treinamento_e_Desenvolvimento",
                "Freq": "MENSAL",
                "Tempo Base": "60m",
                "Impacto Diário Convertido": "2.7m",
                "Eficiência vs 480m": "0.6%",
                "Meta Auditável": "Realizar sessões de treinamento para atualizações sobre legislação trabalhista e compliance, com feedback positivo de 90% dos participantes."
            },
            {
                "Atividade": "Planejamento_Estratégico",
                "Freq": "MENSAL",
                "Tempo Base": "30m",
                "Impacto Diário Convertido": "1.4m",
                "Eficiência vs 480m": "0.3%",
                "Meta Auditável": "Definir e revisar estratégias do Departamento Pessoal, com indicadores de sucesso que demonstrem a melhoria dos processos em pelo menos 15% ao ano."
            }
        ],
        "confronto_pericial": [
            {
                "Atividade": "GESTÃO_DE_ADMISSÕES_E_DEMISSÕES",
                "Origem": "POP PADRÃO",
                "Impacto POP": "60.0m",
                "Impacto Real": "0.0m",
                "Divergência": "-60.0m",
                "Status": "❌ AUSENTE"
            },
            {
                "Atividade": "CONTROLE_DE_PONTO",
                "Origem": "POP PADRÃO",
                "Impacto POP": "60.0m",
                "Impacto Real": "0.0m",
                "Divergência": "-60.0m",
                "Status": "❌ AUSENTE"
            },
            {
                "Atividade": "PROCESSAMENTO_DA_FOLHA_DE_PAGAMENTO",
                "Origem": "POP PADRÃO",
                "Impacto POP": "60.0m",
                "Impacto Real": "0.0m",
                "Divergência": "-60.0m",
                "Status": "❌ AUSENTE"
            },
            {
                "Atividade": "CÁLCULO_DE_FÉRIAS_E_13º_SALÁRIO",
                "Origem": "POP PADRÃO",
                "Impacto POP": "30.0m",
                "Impacto Real": "0.0m",
                "Divergência": "-30.0m",
                "Status": "❌ AUSENTE"
            },
            {
                "Atividade": "GESTÃO_DE_BENEFÍCIOS",
                "Origem": "POP PADRÃO",
                "Impacto POP": "30.0m",
                "Impacto Real": "0.0m",
                "Divergência": "-30.0m",
                "Status": "❌ AUSENTE"
            },
            {
                "Atividade": "ENVIO_DE_OBRIGAÇÕES_LEGAIS",
                "Origem": "POP PADRÃO",
                "Impacto POP": "30.0m",
                "Impacto Real": "0.0m",
                "Divergência": "-30.0m",
                "Status": "❌ AUSENTE"
            },
            {
                "Atividade": "REVISÃO_DE_PROCESSOS_LEGAIS",
                "Origem": "POP PADRÃO",
                "Impacto POP": "12.0m",
                "Impacto Real": "0.0m",
                "Divergência": "-12.0m",
                "Status": "❌ AUSENTE"
            },
            {
                "Atividade": "AUDITORIA_DE_CONFORMIDADE",
                "Origem": "POP PADRÃO",
                "Impacto POP": "12.0m",
                "Impacto Real": "0.0m",
                "Divergência": "-12.0m",
                "Status": "❌ AUSENTE"
            },
            {
                "Atividade": "RELATÓRIOS_DE_GESTÃO",
                "Origem": "POP PADRÃO",
                "Impacto POP": "12.0m",
                "Impacto Real": "0.0m",
                "Divergência": "-12.0m",
                "Status": "❌ AUSENTE"
            },
            {
                "Atividade": "TREINAMENTO_E_DESENVOLVIMENTO",
                "Origem": "POP PADRÃO",
                "Impacto POP": "2.7m",
                "Impacto Real": "0.0m",
                "Divergência": "-2.7m",
                "Status": "❌ AUSENTE"
            },
            {
                "Atividade": "PLANEJAMENTO_ESTRATÉGICO",
                "Origem": "POP PADRÃO",
                "Impacto POP": "1.4m",
                "Impacto Real": "0.0m",
                "Divergência": "-1.4m",
                "Status": "❌ AUSENTE"
            },
            {
                "Atividade": "FECHAMENTO DA FOLHA DE PAGAMENTO (CÁLCULO DE SALÁRIOS, ENCARGOS, BENEFÍCIOS)",
                "Origem": "DESVIO",
                "Impacto POP": "0.0m",
                "Impacto Real": "35.0m",
                "Divergência": "+35.0m",
                "Status": "⚠️ FORA DO PADRÃO"
            },
            {
                "Atividade": "APURAÇÃO E CONFERÊNCIA DE ENCARGOS TRABALHISTAS (INSS, FGTS, IRRF) ",
                "Origem": "DESVIO",
                "Impacto POP": "0.0m",
                "Impacto Real": "35.0m",
                "Divergência": "+35.0m",
                "Status": "⚠️ FORA DO PADRÃO"
            },
            {
                "Atividade": "ENVIO DE OBRIGAÇÕES ACESSÓRIAS (ESOCIAL, DCTFWEB, SEFIP) ",
                "Origem": "DESVIO",
                "Impacto POP": "0.0m",
                "Impacto Real": "20.0m",
                "Divergência": "+20.0m",
                "Status": "⚠️ FORA DO PADRÃO"
            },
            {
                "Atividade": "CONTROLE E GESTÃO DE ADMISSÕES E DEMISSÕES (RESCISÕES, HOMOLOGAÇÕES) ",
                "Origem": "DESVIO",
                "Impacto POP": "0.0m",
                "Impacto Real": "20.0m",
                "Divergência": "+20.0m",
                "Status": "⚠️ FORA DO PADRÃO"
            },
            {
                "Atividade": "INTERPRETAÇÃO E APLICAÇÃO DA LEGISLAÇÃO TRABALHISTA E CONVENÇÕES COLETIVAS ",
                "Origem": "DESVIO",
                "Impacto POP": "0.0m",
                "Impacto Real": "25.0m",
                "Divergência": "+25.0m",
                "Status": "⚠️ FORA DO PADRÃO"
            },
            {
                "Atividade": "ATENDIMENTO INTERNAS E EXTERNAS ",
                "Origem": "DESVIO",
                "Impacto POP": "0.0m",
                "Impacto Real": "30.0m",
                "Divergência": "+30.0m",
                "Status": "⚠️ FORA DO PADRÃO"
            },
            {
                "Atividade": "ANÁLISE DE INCONSISTÊNCIAS NA FOLHA E CORREÇÃO DE DIVERGÊNCIAS ",
                "Origem": "DESVIO",
                "Impacto POP": "0.0m",
                "Impacto Real": "30.0m",
                "Divergência": "+30.0m",
                "Status": "⚠️ FORA DO PADRÃO"
            },
            {
                "Atividade": "GESTÃO DE BENEFÍCIOS (VALE-TRANSPORTE, VALE-ALIMENTAÇÃO, PLANO DE SAÚDE) ",
                "Origem": "DESVIO",
                "Impacto POP": "0.0m",
                "Impacto Real": "20.0m",
                "Divergência": "+20.0m",
                "Status": "⚠️ FORA DO PADRÃO"
            },
            {
                "Atividade": " LANÇAMENTO DE INFORMAÇÕES PARA FOLHA DE PAGAMENTO (HORAS EXTRAS, FALTAS, ADICIONAIS) ",
                "Origem": "DESVIO",
                "Impacto POP": "0.0m",
                "Impacto Real": "25.0m",
                "Divergência": "+25.0m",
                "Status": "⚠️ FORA DO PADRÃO"
            },
            {
                "Atividade": "CONTROLE DE PONTO ELETRÔNICO E TRATAMENTO DE INCONSISTÊNCIAS",
                "Origem": "DESVIO",
                "Impacto POP": "0.0m",
                "Impacto Real": "15.0m",
                "Divergência": "+15.0m",
                "Status": "⚠️ FORA DO PADRÃO"
            },
            {
                "Atividade": "ADMINISTRAÇÃO DE FÉRIAS (PROGRAMAÇÃO, CÁLCULO E CONTROLE)",
                "Origem": "DESVIO",
                "Impacto POP": "0.0m",
                "Impacto Real": "20.0m",
                "Divergência": "+20.0m",
                "Status": "⚠️ FORA DO PADRÃO"
            },
            {
                "Atividade": "CADASTRO E ATUALIZAÇÃO DE DADOS DE COLABORADORES NO SISTEMA",
                "Origem": "DESVIO",
                "Impacto POP": "0.0m",
                "Impacto Real": "10.0m",
                "Divergência": "+10.0m",
                "Status": "⚠️ FORA DO PADRÃO"
            },
            {
                "Atividade": "CONTROLE DE AFASTAMENTOS (INSS, ATESTADOS MÉDICOS, LICENÇAS)",
                "Origem": "DESVIO",
                "Impacto POP": "0.0m",
                "Impacto Real": "15.0m",
                "Divergência": "+15.0m",
                "Status": "⚠️ FORA DO PADRÃO"
            },
            {
                "Atividade": "ATENDIMENTO A COLABORADORES PARA ESCLARECIMENTO DE DÚVIDAS TRABALHISTAS",
                "Origem": "DESVIO",
                "Impacto POP": "0.0m",
                "Impacto Real": "20.0m",
                "Divergência": "+20.0m",
                "Status": "⚠️ FORA DO PADRÃO"
            },
            {
                "Atividade": "ORGANIZAÇÃO E CONFERÊNCIA DE DOCUMENTAÇÃO ADMISSIONAL E DEMISSIONAL",
                "Origem": "DESVIO",
                "Impacto POP": "0.0m",
                "Impacto Real": "20.0m",
                "Divergência": "+20.0m",
                "Status": "⚠️ FORA DO PADRÃO"
            },
            {
                "Atividade": "APOIO NO PROCESSO DE ADMISSÃO E INTEGRAÇÃO DE NOVOS COLABORADORES ",
                "Origem": "DESVIO",
                "Impacto POP": "0.0m",
                "Impacto Real": "40.0m",
                "Divergência": "+40.0m",
                "Status": "⚠️ FORA DO PADRÃO"
            },
            {
                "Atividade": "EMISSÃO DE RELATÓRIOS OPERACIONAIS (FOLHA, PONTO, BENEFÍCIOS)",
                "Origem": "DESVIO",
                "Impacto POP": "0.0m",
                "Impacto Real": "10.0m",
                "Divergência": "+10.0m",
                "Status": "⚠️ FORA DO PADRÃO"
            },
            {
                "Atividade": "CONTROLE DE BENEFÍCIOS (INCLUSÃO, EXCLUSÃO E AJUSTES) ",
                "Origem": "DESVIO",
                "Impacto POP": "0.0m",
                "Impacto Real": "20.0m",
                "Divergência": "+20.0m",
                "Status": "⚠️ FORA DO PADRÃO"
            },
            {
                "Atividade": "ARQUIVAMENTO E ORGANIZAÇÃO DE DOCUMENTOS FÍSICOS E DIGITAIS ",
                "Origem": "DESVIO",
                "Impacto POP": "0.0m",
                "Impacto Real": "15.0m",
                "Divergência": "+15.0m",
                "Status": "⚠️ FORA DO PADRÃO"
            },
            {
                "Atividade": "DIGITALIZAÇÃO DE DOCUMENTOS DE COLABORADORES ",
                "Origem": "DESVIO",
                "Impacto POP": "0.0m",
                "Impacto Real": "15.0m",
                "Divergência": "+15.0m",
                "Status": "⚠️ FORA DO PADRÃO"
            },
            {
                "Atividade": "ATUALIZAÇÃO SIMPLES DE PLANILHAS DE CONTROLE ",
                "Origem": "DESVIO",
                "Impacto POP": "0.0m",
                "Impacto Real": "15.0m",
                "Divergência": "+15.0m",
                "Status": "⚠️ FORA DO PADRÃO"
            },
            {
                "Atividade": "CONFERÊNCIA BÁSICA DE DOCUMENTOS (CHECKLIST ADMISSIONAL/DEMISSIONAL)",
                "Origem": "DESVIO",
                "Impacto POP": "0.0m",
                "Impacto Real": "20.0m",
                "Divergência": "+20.0m",
                "Status": "⚠️ FORA DO PADRÃO"
            },
            {
                "Atividade": "EMISSÃO DE DOCUMENTOS PADRONIZADOS (DECLARAÇÕES, COMPROVANTES)",
                "Origem": "DESVIO",
                "Impacto POP": "0.0m",
                "Impacto Real": "25.0m",
                "Divergência": "+25.0m",
                "Status": "⚠️ FORA DO PADRÃO"
            },
            {
                "Atividade": "APOIO NO ENVIO DE COMUNICADOS INTERNOS",
                "Origem": "DESVIO",
                "Impacto POP": "0.0m",
                "Impacto Real": "15.0m",
                "Divergência": "+15.0m",
                "Status": "⚠️ FORA DO PADRÃO"
            },
            {
                "Atividade": "SEPARAÇÃO DE DOCUMENTOS PARA PROCESSOS INTERNOS ",
                "Origem": "DESVIO",
                "Impacto POP": "0.0m",
                "Impacto Real": "15.0m",
                "Divergência": "+15.0m",
                "Status": "⚠️ FORA DO PADRÃO"
            },
            {
                "Atividade": "ATUALIZAÇÃO DE CADASTROS SIMPLES NO SISTEMA",
                "Origem": "DESVIO",
                "Impacto POP": "0.0m",
                "Impacto Real": "15.0m",
                "Divergência": "+15.0m",
                "Status": "⚠️ FORA DO PADRÃO"
            },
            {
                "Atividade": "CONTROLE DE RECEBIMENTO DE DOCUMENTOS PENDENTES",
                "Origem": "DESVIO",
                "Impacto POP": "0.0m",
                "Impacto Real": "10.0m",
                "Divergência": "+10.0m",
                "Status": "⚠️ FORA DO PADRÃO"
            }
        ],
        "aderencia_cargo_pct": 55.9,
        "total_pop_min": 310.1,
        "total_real_min": 555,
        "risco_operacional": "ALTO",
        "cargo_auditado": "ANALISTA DEPARTAMENTO PESSOAL",
        "gerado_em": "10/05/2026 16:52:49"
    },
    "parecer_360": {
        "parecer_executivo": "A análise das tarefas executadas por Juarez Queiroz Pereira como Analista de Departamento Pessoal revela um alinhamento geral entre o objetivo do cargo e as tarefas relatadas, sendo as principais atividades diretamente relacionadas à gestão administrativa e legal dos colaboradores, conforme definido pelo objetivo. No entanto, a focalização em tarefas altamente operacionais, como arquivamento e atualização de planilhas, sugere um desperdício de formação e competências, considerando a extensa lista de cursos técnicos e avançados. A presença de um perfil DISC predominantemente 'A' (ou seja, orientado para a Ação) combinado com 'C' (Consciência) e 'D' (Dominância) sugere um colaborador que é mais eficaz em ambientes dinâmicos e que possivelmente se sente subutilizado em tarefas repetitivas e de baixa complexidade. As atividades diárias totalizam 405 minutos, dentro do limite de um dia de trabalho regular de 480 minutos. No entanto, as dificuldades relatadas, como dependência de informações de outros setores e frequente necessidade de atualização devido a alterações legais, podem aumentar a carga de trabalho percebida, justificando a necessidade de intervenções. A ausência de atividades focadas em análises estratégicas destaca um desequilíbrio entre capacidades e a rotina atual. Sugere-se uma reavaliação para evitar o risco de Burnout mascarado devido a uma potencial sobrecarga cognitiva.",
        "pop_benchmark": [
            {
                "Atividade": "Fechamento da folha de pagamento",
                "Freq": "D",
                "Tempo": "35 min",
                "Meta": "100% precisão, no prazo"
            },
            {
                "Atividade": "Apuração de encargos trabalhistas",
                "Freq": "D",
                "Tempo": "35 min",
                "Meta": "Compliance 100%"
            },
            {
                "Atividade": "Envio de obrigações acessórias",
                "Freq": "D",
                "Tempo": "20 min",
                "Meta": "98% envio no prazo"
            },
            {
                "Atividade": "Gestão de admissões e demissões",
                "Freq": "D",
                "Tempo": "20 min",
                "Meta": "100% cumprimento legal"
            },
            {
                "Atividade": "Interpretação da legislação trabalhista",
                "Freq": "D",
                "Tempo": "25 min",
                "Meta": "Atualização 98%"
            },
            {
                "Atividade": "Controle de ponto eletrônico",
                "Freq": "D",
                "Tempo": "15 min",
                "Meta": "95% consistência"
            }
        ],
        "veredito_final": "A organização deve focar em parar atividades de baixa complexidade e operacionais, que desperdiçam as competências avançadas do colaborador, tais como arquivamento e digitalização de documentos, que podem ser delegadas ou automatizadas. É crucial estabelecer um foco imediato na automação de processos e na melhoria da comunicação interdepartamental para reduzir a dependência de informações externas. Juarez deve ser direcionado para atividades que reforcem seu perfil de ação e consciência estratégica, o que poderia ser um melhor aproveitamento de suas competências e energia em análises complexas e estratégicas.",
        "cargo_auditado": "ANALISTA DEPARTAMENTO PESSOAL",
        "gerado_em": "10/05/2026 16:52:55"
    },
    "kpis_auditados": {
        "Precisão no Cálculo de Férias e 13º Salário": {
            "percentual_alcance": 66.66,
            "status_pericial": "PARCIAL",
            "analise_critica": "Embora o documento fornecido seja apropriado e os dados estejam de acordo com o relato, a presença de uma divergência corrigida antes do pagamento sugere uma Falha inicial no processo. Isto impacta negativamente na completude, pois o objetivo era a conformidade total sem erros iniciais. A tempestividade está correta, pois as ações corretivas ocorreram antes do pagamento. No entanto, a falha inicial impede que o objetivo de 100% de conformidade sem correções seja considerado atingido.",
            "gap_de_conformidade": [
                "Conformidade inicial total sem necessidade de correções"
            ],
            "ponderacao": {
                "aderencia": 25,
                "integridade": 25,
                "tempestividade": 25,
                "completude": 15
            },
            "relato_auditor": "Verificar e validar os cálculos de férias e 13º salário do trimestre auditado, confirmando conformidade com a CLT e acordos coletivos vigentes, sem erros ou reincidências identificadas no período.",
            "auditado_em": "10/05/2026 16:59:42"
        }
    },
    "produtividade": {
        "eficiencia_real_pct": 13.3,
        "kpis_auditados_total": 1,
        "kpi_critico": "Precisão no Cálculo de Férias e 13º Salário",
        "kpi_critico_score": 66.7,
        "kpis_detalhados": {
            "Precisão no Cálculo de Férias e 13º Salário": {
                "percentual_alcance": 66.66,
                "status_pericial": "PARCIAL",
                "analise_critica": "Embora o documento fornecido seja apropriado e os dados estejam de acordo com o relato, a presença de uma divergência corrigida antes do pagamento sugere uma Falha inicial no processo. Isto impacta negativamente na completude, pois o objetivo era a conformidade total sem erros iniciais. A tempestividade está correta, pois as ações corretivas ocorreram antes do pagamento. No entanto, a falha inicial impede que o objetivo de 100% de conformidade sem correções seja considerado atingido.",
                "gap_de_conformidade": [
                    "Conformidade inicial total sem necessidade de correções"
                ]
            }
        },
        "consolidado_em": "11/05/2026 22:20:36"
    },
    "evidencias_kpi": {
        "documentos_por_kpi": {
            "Precisão no Cálculo de Férias e 13º Salário": "1. Espelho de Folha ERP  \n   Periodicidade: Mensal  \n   Como obter: ERP → [Folha de Pagamento] → competência → Export  \n\n2. Portal eSocial → Consulta de Eventos → competência → Export PDF  \n   Periodicidade: Mensal  \n   Como obter: Portal eSocial → Consulta de Eventos → competência → Export PDF  "
        },
        "total_kpis": 1,
        "gerado_em": "10/05/2026 17:04:19"
    },
    "comparativo_cargo": {
        "cargo": "ANALISTA DEPARTAMENTO PESSOAL",
        "eficiencia_pct": 0.0,
        "posicao_ranking": 1,
        "total_no_cargo": 3,
        "ranking_completo": [
            {
                "Colaborador": "JUAREZ QUEIROZ PEREIRA",
                "Eficiência (%)": "0.0%"
            },
            {
                "Colaborador": "MOACIR JÚNIOR",
                "Eficiência (%)": "0.0%"
            },
            {
                "Colaborador": "THAIS KEYTIANNE MENDONÇA PEREIRA",
                "Eficiência (%)": "0.0%"
            }
        ],
        "comparado_em": "11/05/2026 21:30:39"
    },
    "laudo_central": {
        "texto": "# LAUDO PERICIAL INDIVIDUAL\n\n## 1. IDENTIDADE OPERACIONAL\n- **Nome:** Juarez Queiroz Pereira\n- **Cargo:** Analista Departamento Pessoal\n- **Perfil DISC Dominante:** D\n- **Status de Carga Horária:** 14.5 horas/dia (sobrecarga)\n\n## 2. DIAGNÓSTICO DE ROI AUDITADO\n- **ROI Auditado:** R$ 6,224.17\n- **Horas Recuperáveis:** 177.83\n- **Ganho em Dias:** 22.2\n\nA metodologia de auditoria pericial aplicada considera as sugestões do colaborador, classificadas em três categorias com diferentes ponderações:\n- **Transformação Digital (automação, IA, sistemas, integração):** 85% do potencial\n- **Otimização de Processo (padronização, POP, checklist, treinamento):** 45% do potencial\n- **Melhoria Incremental (demais melhorias operacionais):** 20% do potencial\n\n**Base de Cálculo:** Custo Total de Ocupação de R$ 35,00/hora.\n\n**Fórmula:** Horas declaradas x Frequência anual x Fator de ponderação x R$ 35,00.\n\nO ROI auditado é menor que o bruto devido à aplicação de rigor técnico.\n\n### Sugestões do Colaborador:\n1. **Implantação de processos padronizados para rotinas de admissão, demissão e fechamento de folha, reduzindo erros e retrabalho.** (Categoria: Melhoria Incremental)\n2. **Criação de um cronograma mensal integrado com todos os setores, garantindo o envio de informações dentro dos prazos.** (Categoria: Transformação Digital)\n3. **Investimento em automação de processos (sistemas de folha e ponto), visando maior agilidade e confiabilidade nos dados.** (Categoria: Transformação Digital)\n4. **Realização de treinamentos periódicos para gestores e colaboradores sobre rotinas trabalhistas e uso correto do ponto eletrônico.** (Categoria: Otimização de Processo)\n5. **Melhoria na integração entre os sistemas (folha, ponto e benefícios), evitando divergências de informações.** (Categoria: Transformação Digital)\n6. **Desenvolvimento de indicadores (KPIs) para acompanhamento de erros, retrabalho e cumprimento de prazos.** (Categoria: Melhoria Incremental)\n7. **Centralização e digitalização de documentos, facilitando o acesso e reduzindo perdas de informação.** (Categoria: Melhoria Incremental)\n8. **Criação de canais de comunicação mais claros com colaboradores para esclarecimento de dúvidas sobre folha e benefícios.** (Categoria: Transformação Digital)\n9. **Revisão contínua dos processos internos para adequação às mudanças na legislação trabalhista.** (Categoria: Melhoria Incremental)\n10. **Redução de atividades operacionais por meio de delegação ou automação, permitindo maior foco em análises estratégicas.** (Categoria: Melhoria Incremental)\n\n## 3. ANÁLISE COMPORTAMENTAL\n- **Perfil DISC:** D (Dominância)\n- **Aderência ao Cargo:** 55.9%\n- **Pontos Fortes:** Capacidade de ação e tomada de decisão rápida.\n- **Riscos:** Baixa aderência ao cargo, potencial subutilização em tarefas repetitivas.\n\n## 4. AUDITORIA DE PROCESSOS E NEXO CAUSAL\n### Nexo Causal:\n- **Score:** 61.0\n- **Horas por Dia:** 14.5\n- **Status:** Sobrecarga\n- **Desvio:** 14.5 - 8 = 6.5 horas. O impacto é uma carga de trabalho excessiva, que pode levar a estresse e burnout.\n\n### Aderência ao POP:\n- **Percentual de Aderência ao Cargo:** 55.9%\n- **Total POP Mínimo:** 310.1 minutos\n- **Total Real Mínimo:** 555 minutos\n- **Risco Operacional:** Alto\n\n### Confronto Pericial:\n- **Status ❌ AUSENTE:**\n  - Gestão de Admissões e Demissões: Impacto POP - 60.0m, Impacto Real - 0.0m, Divergência - -60.0m\n  - Controle de Ponto: Impacto POP - 60.0m, Impacto Real - 0.0m, Divergência - -60.0m\n  - Processamento da Folha de Pagamento: Impacto POP - 60.0m, Impacto Real - 0.0m, Divergência - -60.0m\n  - Cálculo de Férias e 13º Salário: Impacto POP - 30.0m, Impacto Real - 0.0m, Divergência - -30.0m\n  - Gestão de Benefícios: Impacto POP - 30.0m, Impacto Real - 0.0m, Divergência - -30.0m\n  - Envio de Obrigações Legais: Impacto POP - 30.0m, Impacto Real - 0.0m, Divergência - -30.0m\n  - Revisão de Processos Legais: Impacto POP - 12.0m, Impacto Real - 0.0m, Divergência - -12.0m\n  - Auditoria de Conformidade: Impacto POP - 12.0m, Impacto Real - 0.0m, Divergência - -12.0m\n  - Relatórios de Gestão: Impacto POP - 12.0m, Impacto Real - 0.0m, Divergência - -12.0m\n  - Treinamento e Desenvolvimento: Impacto POP - 2.7m, Impacto Real - 0.0m, Divergência - -2.7m\n  - Planejamento Estratégico: Impacto POP - 1.4m, Impacto Real - 0.0m, Divergência - -1.4m\n\n- **Status ⚠️ FORA DO PADRÃO:**\n  - Fechamento da Folha de Pagamento: Impacto Real - 35.0m\n  - Apuração e Conferência de Encargos Trabalhistas: Impacto Real - 35.0m\n  - Envio de Obrigações Acessórias: Impacto Real - 20.0m\n  - Controle e Gestão de Admissões e Demissões: Impacto Real - 20.0m\n  - Interpretação e Aplicação da Legislação Trabalhista: Impacto Real - 25.0m\n  - Atendimento Internas e Externas: Impacto Real - 30.0m\n  - Análise de Inconsistências na Folha: Impacto Real - 30.0m\n  - Gestão de Benefícios: Impacto Real - 20.0m\n  - Lançamento de Informações para Folha de Pagamento: Impacto Real - 25.0m\n  - Controle de Ponto Eletrônico: Impacto Real - 15.0m\n  - Administração de Férias: Impacto Real - 20.0m\n  - Cadastro e Atualização de Dados: Impacto Real - 10.0m\n  - Controle de Afastamentos: Impacto Real - 15.0m\n  - Atendimento a Colaboradores: Impacto Real - 20.0m\n  - Organização de Documentação: Impacto Real - 20.0m\n  - Apoio no Processo de Admissão: Impacto Real - 40.0m\n  - Emissão de Relatórios Operacionais: Impacto Real - 10.0m\n  - Controle de Benefícios: Impacto Real - 20.0m\n  - Arquivamento e Organização de Documentos: Impacto Real - 15.0m\n  - Digitalização de Documentos: Impacto Real - 15.0m\n  - Atualização de Planilhas: Impacto Real - 15.0m\n  - Conferência de Documentos: Impacto Real - 20.0m\n  - Emissão de Documentos Padronizados: Impacto Real - 25.0m\n  - Apoio no Envio de Comunicados: Impacto Real - 15.0m\n  - Separação de Documentos: Impacto Real - 15.0m\n  - Atualização de Cadastros: Impacto Real - 15.0m\n  - Controle de Recebimento de Documentos: Impacto Real - 10.0m\n\n### Veredito 360°:\n- **PARAR:** Atividades de baixa complexidade e operacionais, como arquivamento e digitalização de documentos.\n- **DELEGAR:** Tarefas operacionais podem ser delegadas a colaboradores com perfil S (Estabilidade) para permitir que Juarez se concentre em análises estratégicas.\n- **FOCAR:** Automação de processos e melhoria da comunicação interdepartamental.\n\n## 5. PRODUTIVIDADE E KPIs\n- **KPIs Auditados:**\n  - **Precisão no Cálculo de Férias e 13º Salário:** \n    - Percentual de Alcance: 66.66%\n    - Status Pericial: PARCIAL\n    - Análise Crítica: Divergência corrigida antes do pagamento, mas falha inicial impede 100% de conformidade.\n    - Gap de Conformidade: Conformidade inicial total sem necessidade de correções.\n\n- **KPI Crítico:** Precisão no Cálculo de Férias e 13º Salário (Score: 66.7)\n- **Eficiência Real:** 13.3%\n- **Gap de Conformidade:** Conformidade inicial total sem necessidade de correções.\n- **Documentos por KPI:** \n  1. Espelho de Folha ERP (Mensal)\n  2. Portal eSocial (Mensal)\n\n## 6. VEREDITO PERICIAL\n- **PARAR:** Atividades de baixa complexidade e operacionais, como arquivamento e digitalização de documentos, que desperdiçam competências avançadas.\n- **DELEGAR:** Tarefas operacionais a colaboradores com perfil S (Estabilidade).\n- **FOCAR:** Automação de processos e melhoria da comunicação interdepartamental.\n\n## 7. PLANO DE AÇÃO ESTRATÉGICO\n### Ação 1: Criação de um cronograma mensal integrado com todos os setores\n- **Categoria:** Transformação Digital\n- **Impacto Financeiro:** R$ 1,090.83\n- **Horas Recuperáveis:** 31.2 h/ano\n- **Cronograma:**\n  - Semana 1-2: Planejamento do cronograma.\n  - Semana 3-4: Implementação do cronograma.\n  - Mês 2: Validação do cronograma.\n  - Mês 3: Consolidação e ajustes.\n- **Responsável:** Colaborador com perfil D (Dominância).\n- **Como medir:** Acompanhamento de prazos e cumprimento de metas.\n- **ROI acumulado ao final:** R$ 1,090.83\n\n### Ação 2: Investimento em automação de processos\n- **Categoria:** Transformação Digital\n- **Impacto Financeiro:** R$ 1,090.83\n- **Horas Recuperáveis:** 31.2 h/ano\n- **Cronograma:**\n  - Semana 1-2: Levantamento de necessidades.\n  - Semana 3-4: Seleção de ferramentas.\n  - Mês 2: Implement",
        "gerado_em": "10/05/2026 17:12:28"
    },
    "ultima_atualizacao": "11/05/2026 22:20:36"
}